{
  "appPageId" : "baed5a42-32d7-4e02-8500-3aa7e76c7d4b",
  "componentName" : "siteforce:sldsOneColLayout",
  "id" : "2402c4c9-6286-4f05-9900-baae95104bd6",
  "label" : "User Profile",
  "regions" : [ {
    "id" : "e1b5092c-0c9d-4964-9e7c-76a42b46facc",
    "regionName" : "header",
    "type" : "region"
  }, {
    "id" : "b1d41cd1-16a0-4c1b-91dd-c976774c7cb9",
    "regionName" : "content",
    "type" : "region"
  }, {
    "id" : "29ad1c47-5c7e-4642-b89a-0f3d07d68850",
    "regionName" : "footer",
    "type" : "region"
  } ],
  "themeLayoutType" : "Inner",
  "type" : "view",
  "viewType" : "detail-005"
}